{
  "resources": [
    {
      "path": "data.csv",
      "name": "data",
      "profile": "tabular-data-resource",
      "scheme": "file",
      "format": "csv",
      "hashing": "md5",
      "encoding": "utf-8",
      "schema": {
        "fields": [
          {
            "name": "Value",
            "type": "number",
            "title": "Value"
          },
          {
            "name": "Year",
            "type": "number",
            "title": "Year"
          }
        ]
      }
    }
  ],
  "profile": "data-package",
  "name": "4-2-1",
  "title": "ອັດຕາສ່ວນຂອງເດັກນ້ອຍອາຍຸຕ່ ຳ ກວ່າ 5 ປີທີ່ມີການພັດທະນາທາງດ້ານສຸຂະພາບ, ການຮຽນຮູ້ແລະສະຫວັດດີການທາງຈິດໃຈ, ທາງເພດ"
}